samdata_terminal_dev/__init__.py
samdata_terminal_dev/core/__init__.py
samdata_terminal_dev/core/basic.py
samdata_terminal_dev/core/consumer.py
samdata_terminal_dev/core/env.py
samdata_terminal_dev/core/producer.py
samdata_terminal_dev/core/storage.py
samdata_terminal_dev/core/utils.py
samdata_terminal_dev/dbconn/__init__.py
samdata_terminal_dev/dbconn/db_config.py
samdata_terminal_dev/dbconn/mysqlconn.py
samdata_terminal_dev/dbconn/postgresqlconn.py
samdata_terminal_dev/exceptions/__init__.py
samdata_terminal_dev/exceptions/dataexception.py
samdata_terminal_dev/helper/__init__.py
samdata_terminal_dev/helper/loghelper.py
samdata_terminal_dev/helper/mysqlhelper.py
samdata_terminal_dev/helper/pghelper.py
samdata_terminal_dev/market/__init__.py
samdata_terminal_dev/market/database.py
samdata_terminal_dev/market/datafeed.py
samdata_terminal_dev/market/datagetting_sdk.py
samdata_terminal_dev/market/dataproducer.py
samdata_terminal_dev/market/lamx_dataproducer.py
samdata_terminal_dev/market/live_dataproducer.py
samdata_terminal_dev/model/__init__.py
samdata_terminal_dev/model/data_model.py
samdata_terminal_dev/model/order.py
samdata_terminal_dev/model/symbol.py
samdata_terminal_dev/model/sql/__init__.py
samdata_terminal_dev/model/sql/tables.py
samdata_terminal_dev/trade/__init__.py
samdata_terminal_dev/trade/ibmanager.py
samdata_terminal_dev/trade/lmaxmanager.py
samdata_terminal_dev/trade/manager.py
samdata_terminal_dev-2.5.5.dist-info/METADATA
samdata_terminal_dev-2.5.5.dist-info/WHEEL
samdata_terminal_dev-2.5.5.dist-info/top_level.txt
samdata_terminal_dev-2.5.5.dist-info/RECORD
